mindtrace/apps/__init__.py
mindtrace_apps-0.8.0.dist-info/licenses/LICENSE
mindtrace_apps-0.8.0.dist-info/METADATA
mindtrace_apps-0.8.0.dist-info/WHEEL
mindtrace_apps-0.8.0.dist-info/top_level.txt
mindtrace_apps-0.8.0.dist-info/RECORD
