Metadata-Version: 2.4
Name: mindtrace-apps
Version: 0.8.0
Summary: Applications for Mindtrace
Author: Mindtrace Team
License-Expression: Apache-2.0
Project-URL: Homepage, https://mindtrace.ai
Project-URL: Repository, https://github.com/mindtrace/mindtrace/blob/main/mindtrace/apps
Classifier: Programming Language :: Python :: 3
Classifier: Programming Language :: Python :: 3.12
License-File: LICENSE
Requires-Dist: mindtrace-core>=0.8.0
Requires-Dist: mindtrace-registry>=0.8.0
Requires-Dist: mindtrace-database>=0.8.0
Requires-Dist: mindtrace-services>=0.8.0
Requires-Dist: mindtrace-datalake>=0.8.0
Requires-Dist: mindtrace-models>=0.8.0
Requires-Dist: mindtrace-cluster>=0.8.0
Requires-Dist: mindtrace-jobs>=0.8.0
Requires-Dist: mindtrace-hardware>=0.8.0
Requires-Dist: mindtrace-ui>=0.8.0
Requires-Dist: mindtrace-automation>=0.8.0
Dynamic: license-file
